diffsort/__init__.py
diffsort/diffsort.py
diffsort/functional.py
diffsort/networks.py
diffsort-0.2.0.dist-info/LICENSE
diffsort-0.2.0.dist-info/METADATA
diffsort-0.2.0.dist-info/WHEEL
diffsort-0.2.0.dist-info/top_level.txt
diffsort-0.2.0.dist-info/RECORD
